alibabacloud_openplatform20191219/__init__.py
alibabacloud_openplatform20191219/client.py
alibabacloud_openplatform20191219/models.py
alibabacloud_openplatform20191219-2.0.0.dist-info/LICENSE
alibabacloud_openplatform20191219-2.0.0.dist-info/METADATA
alibabacloud_openplatform20191219-2.0.0.dist-info/WHEEL
alibabacloud_openplatform20191219-2.0.0.dist-info/top_level.txt
alibabacloud_openplatform20191219-2.0.0.dist-info/RECORD
